CHANGES.txt
LICENSE.txt
MANIFEST.in
README.txt
setup.py
src/j01/__init__.py
src/j01.select.egg-info/PKG-INFO
src/j01.select.egg-info/SOURCES.txt
src/j01.select.egg-info/dependency_links.txt
src/j01.select.egg-info/namespace_packages.txt
src/j01.select.egg-info/not-zip-safe
src/j01.select.egg-info/requires.txt
src/j01.select.egg-info/top_level.txt
src/j01/select/__init__.py
src/j01/select/configure.zcml
src/j01/select/interfaces.py
src/j01/select/widget.py
src/j01/select/widget_input.pt
src/j01/select/css/j01.select.css
src/j01/select/img/j01Select.png
src/j01/select/img/j01SelectToken.png
src/j01/select/img/j01SelectTokenLeft.gif
src/j01/select/img/j01SelectTokenRight.gif
src/j01/select/js/j01.select.js